server_pack/__init__.py
server_pack/server.py
server_pack/common/__init__.py
server_pack/common/config_path_file.py
server_pack/common/decorators.py
server_pack/common/descriptor.py
server_pack/common/erros.py
server_pack/common/metaclasses.py
server_pack/common/utils.py
server_pack/logs/__init__.py
server_pack/logs/client_log_config.py
server_pack/logs/server_log_config.py
server_pack/server_pack/__init__.py
server_pack/server_pack/kernel.py
server_pack/server_pack/register_user.py
server_pack/server_pack/remove_user.py
server_pack/server_pack/server_gui.py
server_pack/server_pack/server_storage.py
server_pack/unit_tests/__init__.py
server_pack/unit_tests/test_client.py
server_pack/unit_tests/test_server.py
server_pack/unit_tests/test_utils.py
robot_messenger_server-0.1.0.dist-info/METADATA
robot_messenger_server-0.1.0.dist-info/WHEEL
robot_messenger_server-0.1.0.dist-info/top_level.txt
robot_messenger_server-0.1.0.dist-info/RECORD
