Metadata-Version: 2.1
Name: robot-messenger-server
Version: 0.1.0
Summary: Server for messenger
Home-page: UNKNOWN
Author: Eugene Kaddo
Author-email: message.chaos628@gmail.com
License: UNKNOWN
Platform: UNKNOWN
Requires-Dist: PyQt5
Requires-Dist: pycryptodome
Requires-Dist: pycryptodomex
Requires-Dist: sqlalchemy
